pyswi/__init__.py
pyswi/iterative_storage.py
pyswi/iterative_swi.py
pyswi/swi_calc_routines.c
pyswi/swi_calc_routines.cp312-win32.pyd
pyswi/swi_calc_routines.pyx
pyswi/swi_ts.py
pyswi-2.0.3.dist-info/licenses/AUTHORS.rst
pyswi-2.0.3.dist-info/licenses/LICENSE.txt
pyswi-2.0.3.dist-info/METADATA
pyswi-2.0.3.dist-info/WHEEL
pyswi-2.0.3.dist-info/top_level.txt
pyswi-2.0.3.dist-info/RECORD
